MovieHelper/MovieLink.py
MovieHelper/__init__.py
MovieHelper-0.0.2.dist-info/LICENSE
MovieHelper-0.0.2.dist-info/METADATA
MovieHelper-0.0.2.dist-info/WHEEL
MovieHelper-0.0.2.dist-info/top_level.txt
MovieHelper-0.0.2.dist-info/RECORD
