Metadata-Version: 2.1
Name: MovieHelper
Version: 0.0.2
Summary: Help Get Movie Link
Home-page: https://github.com/pypa/sampleproject
Author: Naruto
Author-email: findjobs2019@126.com
License: UNKNOWN
Project-URL: Bug Tracker, https://github.com/pypa/sampleproject/issues
Platform: UNKNOWN
Classifier: Programming Language :: Python :: 3
Classifier: License :: OSI Approved :: MIT License
Classifier: Operating System :: OS Independent
Requires-Python: >=3.6
License-File: LICENSE
